[{"items":[],"customer":{"fullName":"Jaji Moshood","number":"08090686548","email":"Jaji.moshood1297@gmail.com","address":"Lagos","direction":"ikorodu","payMethod":"PayOnDelivery"},"id":"437.2254046101571"},{"id":"678.4960486041875","items":[{"id":"m40","name":"Breakfast Appetizer","price":50,"description":"lorem ipsumhhf jhkrifr aspertjd mongodnr fffh urrr gkrbrefk","image":"appetizer.jpg","imageAlt":"Breakfast Appetizer","category":"appetizer","quantity":1},{"id":"m41","name":"Breakfast light Appetizer","price":20,"description":"lorem ipsumhhf jhkrifr aspertjd mongodnr fffh urrr gkrbrefk ","image":"breakfast.jpeg","imageAlt":"Breakfast light Appetizer","category":"appetizer","quantity":1},{"id":"m39","name":"Beef Dish","price":100,"description":"Stir fried shredded beef with oyster sauce  with fresh tomatoes with green pepper in black bean sauce","image":"beef-dish.jpg","imageAlt":"Beef Dish","category":"appetizer","quantity":1}],"customer":{"fullName":"Jaji Moshood","number":"08090686548","email":"Jaji.moshood1297@gmail.com","address":"Lagos","direction":"kjjk","payMethod":"PayNow"}},{"id":"582.9777666168047","items":[{"id":"m40","name":"Breakfast Appetizer","price":50,"description":"lorem ipsumhhf jhkrifr aspertjd mongodnr fffh urrr gkrbrefk","image":"appetizer.jpg","imageAlt":"Breakfast Appetizer","category":"appetizer","quantity":1},{"id":"m41","name":"Breakfast light Appetizer","price":20,"description":"lorem ipsumhhf jhkrifr aspertjd mongodnr fffh urrr gkrbrefk ","image":"breakfast.jpeg","imageAlt":"Breakfast light Appetizer","category":"appetizer","quantity":1},{"id":"m39","name":"Beef Dish","price":100,"description":"Stir fried shredded beef with oyster sauce  with fresh tomatoes with green pepper in black bean sauce","image":"beef-dish.jpg","imageAlt":"Beef Dish","category":"appetizer","quantity":1}],"customer":{"fullName":"Jaji Moshood","number":"08090686548","email":"Jaji.moshood1297@gmail.com","address":"Lagos","direction":"this ","payMethod":"PayOnDelivery"},"ToPayment":183.32},{"id":"564.3326694663689","items":[{"id":"m40","name":"Breakfast Appetizer","price":50,"description":"lorem ipsumhhf jhkrifr aspertjd mongodnr fffh urrr gkrbrefk","image":"appetizer.jpg","imageAlt":"Breakfast Appetizer","category":"appetizer","quantity":1},{"id":"m39","name":"Beef Dish","price":100,"description":"Stir fried shredded beef with oyster sauce  with fresh tomatoes with green pepper in black bean sauce","image":"beef-dish.jpg","imageAlt":"Beef Dish","category":"appetizer","quantity":1},{"id":"m41","name":"Breakfast light Appetizer","price":20,"description":"lorem ipsumhhf jhkrifr aspertjd mongodnr fffh urrr gkrbrefk ","image":"breakfast.jpeg","imageAlt":"Breakfast light Appetizer","category":"appetizer","quantity":1}],"customer":{"fullName":"Jaji Moshood","number":"08090686548","email":"Jaji.moshood1297@gmail.com","address":"Lagos","direction":"jkkkk","payMethod":"PayOnDelivery","Amount":183.32}},{"id":"818.7186117458316","items":[{"id":"m39","name":"Beef Dish","price":100,"description":"Stir fried shredded beef with oyster sauce  with fresh tomatoes with green pepper in black bean sauce","image":"beef-dish.jpg","imageAlt":"Beef Dish","category":"appetizer","quantity":1},{"id":"m40","name":"Breakfast Appetizer","price":50,"description":"lorem ipsumhhf jhkrifr aspertjd mongodnr fffh urrr gkrbrefk","image":"appetizer.jpg","imageAlt":"Breakfast Appetizer","category":"appetizer","quantity":1}],"customer":{"fullName":"Jaji Moshood","phone":"08090686548","email":"Jaji.moshood1297@gmail.com","address":"Lagos","direction":"jj","payMethod":"PayNow","amount":163.32}},{"id":"590.110645390171","items":[{"id":"m39","name":"Beef Dish","price":100,"description":"Stir fried shredded beef with oyster sauce  with fresh tomatoes with green pepper in black bean sauce","image":"beef-dish.jpg","imageAlt":"Beef Dish","category":"appetizer","quantity":1},{"id":"m40","name":"Breakfast Appetizer","price":50,"description":"lorem ipsumhhf jhkrifr aspertjd mongodnr fffh urrr gkrbrefk","image":"appetizer.jpg","imageAlt":"Breakfast Appetizer","category":"appetizer","quantity":1}],"customer":{"fullName":"Jaji Moshood","phone":"08090686548","email":"Jaji.moshood1297@gmail.com","address":"Lagos","direction":"kkkk","payMethod":"PayOnDelivery","amount":163.32}},{"id":"39.912196356687524","items":[{"id":"m39","name":"Beef Dish","price":100,"description":"Stir fried shredded beef with oyster sauce  with fresh tomatoes with green pepper in black bean sauce","image":"beef-dish.jpg","imageAlt":"Beef Dish","category":"appetizer","quantity":1},{"id":"m40","name":"Breakfast Appetizer","price":50,"description":"lorem ipsumhhf jhkrifr aspertjd mongodnr fffh urrr gkrbrefk","image":"appetizer.jpg","imageAlt":"Breakfast Appetizer","category":"appetizer","quantity":1}],"customer":{"fullName":"Jaji Moshood","phone":"08090686548","email":"Jaji.moshood1297@gmail.com","address":"Lagos","direction":"kkk","payMethod":"PayNow","amount":163.32}},{"id":"475.8554537905824","items":[{"id":"m41","name":"Breakfast light Appetizer","price":20,"description":"lorem ipsumhhf jhkrifr aspertjd mongodnr fffh urrr gkrbrefk ","image":"breakfast.jpeg","imageAlt":"Breakfast light Appetizer","category":"appetizer","quantity":1},{"id":"m39","name":"Beef Dish","price":100,"description":"Stir fried shredded beef with oyster sauce  with fresh tomatoes with green pepper in black bean sauce","image":"beef-dish.jpg","imageAlt":"Beef Dish","category":"appetizer","quantity":5}],"customer":{"fullName":"Jaji Moshood","number":"08090686548","email":"Jaji.moshood1297@gmail.com","address":"Lagos","direction":"jjf","payMethod":"PayOnDelivery"}},{"id":"18.894955384099134","items":[{"id":"m41","name":"Breakfast light Appetizer","price":20,"description":"lorem ipsumhhf jhkrifr aspertjd mongodnr fffh urrr gkrbrefk ","image":"breakfast.jpeg","imageAlt":"Breakfast light Appetizer","category":"appetizer","quantity":1},{"id":"m40","name":"Breakfast Appetizer","price":50,"description":"lorem ipsumhhf jhkrifr aspertjd mongodnr fffh urrr gkrbrefk","image":"appetizer.jpg","imageAlt":"Breakfast Appetizer","category":"appetizer","quantity":1}],"customer":{"fullName":"Jaji Moshood","phone":"08090686548","email":"Jaji.moshood1297@gmail.com","address":"Lagos","direction":"988","payMethod":"PayOnDelivery","amount":83.32}},{"id":"860.2931897612675","items":[{"id":"m41","name":"Breakfast light Appetizer","price":20,"description":"lorem ipsumhhf jhkrifr aspertjd mongodnr fffh urrr gkrbrefk ","image":"breakfast.jpeg","imageAlt":"Breakfast light Appetizer","category":"appetizer","quantity":1},{"id":"m40","name":"Breakfast Appetizer","price":50,"description":"lorem ipsumhhf jhkrifr aspertjd mongodnr fffh urrr gkrbrefk","image":"appetizer.jpg","imageAlt":"Breakfast Appetizer","category":"appetizer","quantity":1}],"customer":{"fullName":"Jaji Moshood","phone":"08090686548","email":"Jaji.moshood1297@gmail.com","address":"Lagos","direction":"hi","payMethod":"PayNow","amount":83.32}},{"id":"743.0994588652966","items":[{"id":"m39","name":"Beef Dish","price":100,"description":"Stir fried shredded beef with oyster sauce  with fresh tomatoes with green pepper in black bean sauce","image":"beef-dish.jpg","imageAlt":"Beef Dish","category":"appetizer","quantity":1},{"id":"m40","name":"Breakfast Appetizer","price":50,"description":"lorem ipsumhhf jhkrifr aspertjd mongodnr fffh urrr gkrbrefk","image":"appetizer.jpg","imageAlt":"Breakfast Appetizer","category":"appetizer","quantity":1}],"customer":{"fullName":"Jaji Moshood","phone":"08090686548","email":"Jaji.moshood1297@gmail.com","address":"Lagos","direction":"hi","payMethod":"PayOnDelivery","amount":163.32}},{"id":"372.41394109893247","items":[],"customer":{"fullName":"Jaji Moshood","phone":"08090686548","email":"Jaji.moshood1297@gmail.com","address":"Lagos","direction":"h","payMethod":"PayNow","amount":13.32}},{"id":"521.7348374590198","items":[],"customer":{"fullName":"Jaji Moshood","phone":"08090686548","email":"Jaji.moshood1297@gmail.com","address":"Lagos","direction":"gg","payMethod":"PayNow","amount":13.32}},{"id":"675.5655999362662","items":[],"customer":{"fullName":"Jaji Moshood","phone":"08090686548","email":"Jaji.moshood1297@gmail.com","address":"Lagos","direction":"gg","payMethod":"PayNow","amount":13.32}},{"id":"197.07696534475662","items":[],"customer":{"fullName":"Jaji Moshood","phone":"08090686548","email":"Jaji.moshood1297@gmail.com","address":"Lagos","direction":"gg","payMethod":"PayNow","amount":13.32}},{"id":"433.2927204706063","items":[],"customer":{"fullName":"Jaji Moshood","phone":"08090686548","email":"Jaji.moshood1297@gmail.com","address":"Lagos","direction":"kkk","payMethod":"PayNow","amount":13.32}},{"id":"28.787857633590043","items":[],"customer":{"fullName":"Jaji Moshood","phone":"08090686548","email":"Jaji.moshood1297@gmail.com","address":"Lagos","direction":"kkk","payMethod":"PayNow","amount":13.32}},{"id":"328.99816959679407","items":[],"customer":{"fullName":"Jaji Moshood","phone":"08090686548","email":"Jaji.moshood1297@gmail.com","address":"Lagos","direction":"ppp","payMethod":"PayNow","amount":13.32}},{"id":"706.6942237680305","items":[],"customer":{"fullName":"Jaji Moshood","phone":"08090686548","email":"Jaji.moshood1297@gmail.com","address":"Lagos","direction":"ppp","payMethod":"PayNow","amount":13.32}},{"id":"69.1627811958544","items":[],"customer":{"fullName":"Jaji Moshood","phone":"08090686548","email":"Jaji.moshood1297@gmail.com","address":"Lagos","direction":"ppp","payMethod":"PayNow","amount":13.32}},{"id":"54.901028269110476","items":[],"customer":{"fullName":"Jaji Moshood","phone":"08090686548","email":"Jaji.moshood1297@gmail.com","address":"Lagos","direction":"ppp","payMethod":"PayOnDelivery","amount":13.32}},{"id":"264.07192618000886","items":[{"id":"m39","name":"Beef Dish","price":100,"description":"Stir fried shredded beef with oyster sauce  with fresh tomatoes with green pepper in black bean sauce","image":"beef-dish.jpg","imageAlt":"Beef Dish","category":"appetizer","quantity":1}],"customer":{"fullName":"Jaji Moshood","phone":"08090686548","email":"Jaji.moshood1297@gmail.com","address":"Lagos","direction":"hi","payMethod":"PayOnDelivery","amount":113.32}},{"id":"615.6440167127884","items":[{"id":"m39","name":"Beef Dish","price":100,"description":"Stir fried shredded beef with oyster sauce  with fresh tomatoes with green pepper in black bean sauce","image":"beef-dish.jpg","imageAlt":"Beef Dish","category":"appetizer","quantity":1}],"customer":{"fullName":"Jaji Moshood","phone":"08090686548","email":"Jaji.moshood1297@gmail.com","address":"Lagos","direction":"hi","payMethod":"PayOnDelivery","amount":113.32}},{"id":"85.13147438721136","items":[],"customer":{"fullName":"Jaji Moshood","phone":"08090686548","email":"Jaji.moshood1297@gmail.com","address":"Lagos","direction":"hi ","payMethod":"PayNow","amount":13.32}},{"id":"237.79117375518055","items":[{"id":"m39","name":"Beef Dish","price":100,"description":"Stir fried shredded beef with oyster sauce  with fresh tomatoes with green pepper in black bean sauce","image":"beef-dish.jpg","imageAlt":"Beef Dish","category":"appetizer","quantity":1}],"customer":{"fullName":"Jaji Moshood","phone":"08090686548","email":"Jaji.moshood1297@gmail.com","address":"Lagos","direction":"hi","payMethod":"PayOnDelivery","amount":113.32}},{"id":"447.6176308720967","items":[{"id":"m39","name":"Beef Dish","price":100,"description":"Stir fried shredded beef with oyster sauce  with fresh tomatoes with green pepper in black bean sauce","image":"beef-dish.jpg","imageAlt":"Beef Dish","category":"appetizer","quantity":6}],"customer":{"fullName":"Jaji Moshood","phone":"08090686548","email":"Jaji.moshood1297@gmail.com","address":"Lagos","direction":"hi ","payMethod":"PayNow","amount":613.32}},{"id":"173.93746443497426","items":[{"id":"m39","name":"Beef Dish","price":100,"description":"Stir fried shredded beef with oyster sauce  with fresh tomatoes with green pepper in black bean sauce","image":"beef-dish.jpg","imageAlt":"Beef Dish","category":"appetizer","quantity":6}],"customer":{"fullName":"Jaji Moshood","phone":"08090686548","email":"Jaji.moshood1297@gmail.com","address":"Lagos","direction":"hi ","payMethod":"PayNow","amount":613.32}},{"id":"323.9313360287286","items":[{"id":"m41","name":"Breakfast light Appetizer","price":20,"description":"lorem ipsumhhf jhkrifr aspertjd mongodnr fffh urrr gkrbrefk ","image":"breakfast.jpeg","imageAlt":"Breakfast light Appetizer","category":"appetizer","quantity":5}],"customer":{"fullName":"Jaji Moshood","phone":"08090686548","email":"Jaji.moshood1297@gmail.com","address":"Lagos","direction":"ki","payMethod":"PayNow","amount":113.32}},{"id":"977.5597658253458","items":[{"id":"m41","name":"Breakfast light Appetizer","price":20,"description":"lorem ipsumhhf jhkrifr aspertjd mongodnr fffh urrr gkrbrefk ","image":"breakfast.jpeg","imageAlt":"Breakfast light Appetizer","category":"appetizer","quantity":5}],"customer":{"fullName":"Jaji Moshood","phone":"08090686548","email":"Jaji.moshood1297@gmail.com","address":"Lagos","direction":"ki","payMethod":"PayNow","amount":113.32}},{"id":"572.923034065697","items":[{"id":"m41","name":"Breakfast light Appetizer","price":20,"description":"lorem ipsumhhf jhkrifr aspertjd mongodnr fffh urrr gkrbrefk ","image":"breakfast.jpeg","imageAlt":"Breakfast light Appetizer","category":"appetizer","quantity":5}],"customer":{"fullName":"Jaji Moshood","phone":"08090686548","email":"Jaji.moshood1297@gmail.com","address":"Lagos","direction":"ki","payMethod":"PayNow","amount":113.32}},{"id":"844.176003665775","items":[{"id":"m41","name":"Breakfast light Appetizer","price":20,"description":"lorem ipsumhhf jhkrifr aspertjd mongodnr fffh urrr gkrbrefk ","image":"breakfast.jpeg","imageAlt":"Breakfast light Appetizer","category":"appetizer","quantity":5}],"customer":{"fullName":"Jaji Moshood","phone":"08090686548","email":"Jaji.moshood1297@gmail.com","address":"Lagos","direction":"ki","payMethod":"PayNow","amount":113.32}},{"id":"484.24302974414246","items":[{"id":"m41","name":"Breakfast light Appetizer","price":20,"description":"lorem ipsumhhf jhkrifr aspertjd mongodnr fffh urrr gkrbrefk ","image":"breakfast.jpeg","imageAlt":"Breakfast light Appetizer","category":"appetizer","quantity":5}],"customer":{"fullName":"Jaji Moshood","phone":"08090686548","email":"Jaji.moshood1297@gmail.com","address":"Lagos","direction":"ki","payMethod":"PayNow","amount":113.32}},{"id":"30.37969759933845","items":[{"id":"m41","name":"Breakfast light Appetizer","price":20,"description":"lorem ipsumhhf jhkrifr aspertjd mongodnr fffh urrr gkrbrefk ","image":"breakfast.jpeg","imageAlt":"Breakfast light Appetizer","category":"appetizer","quantity":5}],"customer":{"fullName":"Jaji Moshood","phone":"08090686548","email":"Jaji.moshood1297@gmail.com","address":"Lagos","direction":"ki","payMethod":"PayOnDelivery","amount":113.32}},{"id":"650.1692574627962","items":[{"id":"m41","name":"Breakfast light Appetizer","price":20,"description":"lorem ipsumhhf jhkrifr aspertjd mongodnr fffh urrr gkrbrefk ","image":"breakfast.jpeg","imageAlt":"Breakfast light Appetizer","category":"appetizer","quantity":5}],"customer":{"fullName":"Jaji Moshood","phone":"08090686548","email":"Jaji.moshood1297@gmail.com","address":"Lagos","direction":"ki","payMethod":"PayNow","amount":113.32}},{"id":"642.3600772288669","items":[{"id":"m41","name":"Breakfast light Appetizer","price":20,"description":"lorem ipsumhhf jhkrifr aspertjd mongodnr fffh urrr gkrbrefk ","image":"breakfast.jpeg","imageAlt":"Breakfast light Appetizer","category":"appetizer","quantity":5}],"customer":{"fullName":"Jaji Moshood","phone":"08090686548","email":"Jaji.moshood1297@gmail.com","address":"Lagos","direction":"j","payMethod":"PayNow"}},{"id":"19.83487809391349","items":[{"id":"m41","name":"Breakfast light Appetizer","price":20,"description":"lorem ipsumhhf jhkrifr aspertjd mongodnr fffh urrr gkrbrefk ","image":"breakfast.jpeg","imageAlt":"Breakfast light Appetizer","category":"appetizer","quantity":5}],"customer":{"fullName":"Jaji Moshood","phone":"08090686548","email":"Jaji.moshood1297@gmail.com","address":"Lagos","direction":"k","payMethod":"PayNow"}},{"id":"778.6093448341373","items":[],"customer":{"fullName":"Jaji Moshood","phone":"08090686548","email":"Jaji.moshood1297@gmail.com","address":"Lagos","direction":"j","payMethod":"PayOnDelivery","amount":13.32}},{"id":"886.7876971205975","items":[],"customer":{"fullName":"Jaji Moshood","phone":"08090686548","email":"Jaji.moshood1297@gmail.com","address":"Lagos","direction":"j","payMethod":"PayOnDelivery","amount":13.32}},{"id":"940.6719427817458","items":[],"customer":{"fullName":"Jaji Moshood","phone":"08090686548","email":"Jaji.moshood1297@gmail.com","address":"Lagos","direction":"k","payMethod":"PayNow","amount":13.32}},{"id":"818.7334211865498","items":[],"customer":{"fullName":"Jaji Moshood","phone":"08090686548","email":"Jaji.moshood1297@gmail.com","address":"Lagos","direction":"k","payMethod":"PayNow","amount":13.32}},{"id":"961.318302899197","items":[],"customer":{"fullName":"Jaji Moshood","phone":"08090686548","email":"Jaji.moshood1297@gmail.com","address":"Lagos","direction":"k","payMethod":"PayNow","amount":13.32}},{"id":"464.412802320243","items":[],"customer":{"fullName":"Jaji Moshood","phone":"08090686548","email":"Jaji.moshood1297@gmail.com","address":"Lagos","direction":"k","payMethod":"payOnDelivery","amount":13.32}},{"id":"696.0263779442124","items":[],"customer":{"fullName":"Jaji Moshood","phone":"08090686548","email":"Jaji.moshood1297@gmail.com","address":"Lagos","direction":"k","payMethod":"payOnDelivery","amount":13.32}},{"id":"473.84599054501433","items":[],"customer":{"fullName":"Jaji Moshood","phone":"08090686548","email":"Jaji.moshood1297@gmail.com","address":"Lagos","direction":"k","payMethod":"payOnDelivery","amount":13.32}},{"id":"255.9381918968122","items":[{"id":"m39","name":"Beef Dish","price":100,"description":"Stir fried shredded beef with oyster sauce  with fresh tomatoes with green pepper in black bean sauce","image":"beef-dish.jpg","imageAlt":"Beef Dish","category":"appetizer","quantity":17},{"id":"m40","name":"Breakfast Appetizer","price":50,"description":"lorem ipsumhhf jhkrifr aspertjd mongodnr fffh urrr gkrbrefk","image":"appetizer.jpg","imageAlt":"Breakfast Appetizer","category":"appetizer","quantity":1},{"id":"m41","name":"Breakfast light Appetizer","price":20,"description":"lorem ipsumhhf jhkrifr aspertjd mongodnr fffh urrr gkrbrefk ","image":"breakfast.jpeg","imageAlt":"Breakfast light Appetizer","category":"appetizer","quantity":1}],"customer":{"fullName":"Jaji Moshood","phone":"08090686548","email":"Jaji.moshood1297@gmail.com","address":"Lagos","direction":"k","payMethod":"payOnDelivery","amount":1783.32}},{"id":"684.4404150796182","items":[{"id":"m39","name":"Beef Dish","price":100,"description":"Stir fried shredded beef with oyster sauce  with fresh tomatoes with green pepper in black bean sauce","image":"beef-dish.jpg","imageAlt":"Beef Dish","category":"appetizer","quantity":17},{"id":"m40","name":"Breakfast Appetizer","price":50,"description":"lorem ipsumhhf jhkrifr aspertjd mongodnr fffh urrr gkrbrefk","image":"appetizer.jpg","imageAlt":"Breakfast Appetizer","category":"appetizer","quantity":1},{"id":"m41","name":"Breakfast light Appetizer","price":20,"description":"lorem ipsumhhf jhkrifr aspertjd mongodnr fffh urrr gkrbrefk ","image":"breakfast.jpeg","imageAlt":"Breakfast light Appetizer","category":"appetizer","quantity":1}],"customer":{"fullName":"Jaji Moshood","phone":"08090686548","email":"Jaji.moshood1297@gmail.com","address":"Lagos","direction":"k","payMethod":"payOnDelivery","amount":1783.32}},{"id":"118.37743808223289","items":[{"id":"m39","name":"Beef Dish","price":100,"description":"Stir fried shredded beef with oyster sauce  with fresh tomatoes with green pepper in black bean sauce","image":"beef-dish.jpg","imageAlt":"Beef Dish","category":"appetizer","quantity":17},{"id":"m40","name":"Breakfast Appetizer","price":50,"description":"lorem ipsumhhf jhkrifr aspertjd mongodnr fffh urrr gkrbrefk","image":"appetizer.jpg","imageAlt":"Breakfast Appetizer","category":"appetizer","quantity":1},{"id":"m41","name":"Breakfast light Appetizer","price":20,"description":"lorem ipsumhhf jhkrifr aspertjd mongodnr fffh urrr gkrbrefk ","image":"breakfast.jpeg","imageAlt":"Breakfast light Appetizer","category":"appetizer","quantity":1}],"customer":{"fullName":"Jaji Moshood","phone":"08090686548","email":"Jaji.moshood1297@gmail.com","address":"Lagos","direction":"k","payMethod":"payOnDelivery","amount":1783.32}},{"id":"474.04955343834087","items":[{"id":"m39","name":"Beef Dish","price":100,"description":"Stir fried shredded beef with oyster sauce  with fresh tomatoes with green pepper in black bean sauce","image":"beef-dish.jpg","imageAlt":"Beef Dish","category":"appetizer","quantity":17},{"id":"m40","name":"Breakfast Appetizer","price":50,"description":"lorem ipsumhhf jhkrifr aspertjd mongodnr fffh urrr gkrbrefk","image":"appetizer.jpg","imageAlt":"Breakfast Appetizer","category":"appetizer","quantity":1},{"id":"m41","name":"Breakfast light Appetizer","price":20,"description":"lorem ipsumhhf jhkrifr aspertjd mongodnr fffh urrr gkrbrefk ","image":"breakfast.jpeg","imageAlt":"Breakfast light Appetizer","category":"appetizer","quantity":1}],"customer":{"fullName":"Jaji Moshood","phone":"08090686548","email":"Jaji.moshood1297@gmail.com","address":"Lagos","direction":"j","payMethod":"payOnDelivery","amount":1783.32}},{"id":"655.6954928812213","items":[{"id":"m39","name":"Beef Dish","price":100,"description":"Stir fried shredded beef with oyster sauce  with fresh tomatoes with green pepper in black bean sauce","image":"beef-dish.jpg","imageAlt":"Beef Dish","category":"appetizer","quantity":6},{"id":"m40","name":"Breakfast Appetizer","price":50,"description":"lorem ipsumhhf jhkrifr aspertjd mongodnr fffh urrr gkrbrefk","image":"appetizer.jpg","imageAlt":"Breakfast Appetizer","category":"appetizer","quantity":1}],"customer":{"fullName":"Jaji Moshood","phone":"08090686548","email":"Jaji.moshood1297@gmail.com","address":"Lagos","direction":"k","payMethod":"payOnDelivery","amount":663.32}},{"id":"401.20592126301835","items":[{"id":"m39","name":"Beef Dish","price":100,"description":"Stir fried shredded beef with oyster sauce  with fresh tomatoes with green pepper in black bean sauce","image":"beef-dish.jpg","imageAlt":"Beef Dish","category":"appetizer","quantity":6},{"id":"m40","name":"Breakfast Appetizer","price":50,"description":"lorem ipsumhhf jhkrifr aspertjd mongodnr fffh urrr gkrbrefk","image":"appetizer.jpg","imageAlt":"Breakfast Appetizer","category":"appetizer","quantity":1}],"customer":{"fullName":"Jaji Moshood","phone":"08090686548","email":"Jaji.moshood1297@gmail.com","address":"Lagos","direction":"hi ","payMethod":"payOnDelivery","amount":663.32}},{"id":"964.8347557671597","items":[],"customer":{"fullName":"Jaji Moshood","phone":"08090686548","email":"Jaji.moshood1297@gmail.com","address":"Lagos","direction":"k","payMethod":"payOnDelivery","amount":13.32}},{"id":"514.5906286924162","items":[],"customer":{"fullName":"Jaji Moshood","phone":"08090686548","email":"Jaji.moshood1297@gmail.com","address":"Lagos","direction":"j","payMethod":"payOnDelivery","amount":13.32}},{"id":"632.1901084347159","items":[{"id":"m39","name":"Beef Dish","price":100,"description":"Stir fried shredded beef with oyster sauce  with fresh tomatoes with green pepper in black bean sauce","image":"beef-dish.jpg","imageAlt":"Beef Dish","category":"appetizer","quantity":7},{"id":"m40","name":"Breakfast Appetizer","price":50,"description":"lorem ipsumhhf jhkrifr aspertjd mongodnr fffh urrr gkrbrefk","image":"appetizer.jpg","imageAlt":"Breakfast Appetizer","category":"appetizer","quantity":1}],"customer":{"fullName":"Jaji Moshood","phone":"08090686548","email":"Jaji.moshood1297@gmail.com","address":"Lagos","direction":"j","payMethod":"payOnDelivery","amount":0}},{"id":"294.52181137549127","items":[{"id":"m39","name":"Beef Dish","price":100,"description":"Stir fried shredded beef with oyster sauce  with fresh tomatoes with green pepper in black bean sauce","image":"beef-dish.jpg","imageAlt":"Beef Dish","category":"appetizer","quantity":7},{"id":"m40","name":"Breakfast Appetizer","price":50,"description":"lorem ipsumhhf jhkrifr aspertjd mongodnr fffh urrr gkrbrefk","image":"appetizer.jpg","imageAlt":"Breakfast Appetizer","category":"appetizer","quantity":1}],"customer":{"fullName":"Jaji Moshood","phone":"08090686548","email":"Jaji.moshood1297@gmail.com","address":"Lagos","direction":"j","payMethod":"payOnDelivery","amount":0}},{"id":"757.2949079223029","items":[],"customer":{"fullName":"Jaji Moshood","phone":"08090686548","email":"Jaji.moshood1297@gmail.com","address":"Lagos","direction":"l","payMethod":"payOnDelivery","amount":13.32}},{"id":"569.5958103975416","items":[],"customer":{"fullName":"Jaji Moshood","phone":"08090686548","email":"Jaji.moshood1297@gmail.com","address":"Lagos","direction":"k","payMethod":"payOnDelivery","amount":13.32}},{"id":"404.32709758483765","items":[{"id":"m39","name":"Beef Dish","price":100,"description":"Stir fried shredded beef with oyster sauce  with fresh tomatoes with green pepper in black bean sauce","image":"beef-dish.jpg","imageAlt":"Beef Dish","category":"appetizer","quantity":5},{"id":"m40","name":"Breakfast Appetizer","price":50,"description":"lorem ipsumhhf jhkrifr aspertjd mongodnr fffh urrr gkrbrefk","image":"appetizer.jpg","imageAlt":"Breakfast Appetizer","category":"appetizer","quantity":1},{"id":"m41","name":"Breakfast light Appetizer","price":20,"description":"lorem ipsumhhf jhkrifr aspertjd mongodnr fffh urrr gkrbrefk ","image":"breakfast.jpeg","imageAlt":"Breakfast light Appetizer","category":"appetizer","quantity":1}],"customer":{"fullName":"Jaji Moshood","phone":"08090686548","email":"Jaji.moshood1297@gmail.com","address":"Lagos","direction":"j","payMethod":"payOnDelivery","amount":583.32}},{"id":"273.06686680469295","items":[{"id":"m39","name":"Beef Dish","price":100,"description":"Stir fried shredded beef with oyster sauce  with fresh tomatoes with green pepper in black bean sauce","image":"beef-dish.jpg","imageAlt":"Beef Dish","category":"appetizer","quantity":5},{"id":"m40","name":"Breakfast Appetizer","price":50,"description":"lorem ipsumhhf jhkrifr aspertjd mongodnr fffh urrr gkrbrefk","image":"appetizer.jpg","imageAlt":"Breakfast Appetizer","category":"appetizer","quantity":1},{"id":"m41","name":"Breakfast light Appetizer","price":20,"description":"lorem ipsumhhf jhkrifr aspertjd mongodnr fffh urrr gkrbrefk ","image":"breakfast.jpeg","imageAlt":"Breakfast light Appetizer","category":"appetizer","quantity":1}],"customer":{"fullName":"Jaji Moshood","phone":"08090686548","email":"Jaji.moshood1297@gmail.com","address":"Lagos","direction":"k","payMethod":"payOnDelivery","amount":583.32}},{"id":"706.1055953230925","items":[{"id":"m39","name":"Beef Dish","price":100,"description":"Stir fried shredded beef with oyster sauce  with fresh tomatoes with green pepper in black bean sauce","image":"beef-dish.jpg","imageAlt":"Beef Dish","category":"appetizer","quantity":5},{"id":"m40","name":"Breakfast Appetizer","price":50,"description":"lorem ipsumhhf jhkrifr aspertjd mongodnr fffh urrr gkrbrefk","image":"appetizer.jpg","imageAlt":"Breakfast Appetizer","category":"appetizer","quantity":1},{"id":"m41","name":"Breakfast light Appetizer","price":20,"description":"lorem ipsumhhf jhkrifr aspertjd mongodnr fffh urrr gkrbrefk ","image":"breakfast.jpeg","imageAlt":"Breakfast light Appetizer","category":"appetizer","quantity":1}],"customer":{"fullName":"Jaji Moshood","phone":"08090686548","email":"Jaji.moshood1297@gmail.com","address":"Lagos","direction":"j","payMethod":"payOnDelivery","amount":583.32}},{"id":"291.89877532743935","items":[{"id":"m39","name":"Beef Dish","price":100,"description":"Stir fried shredded beef with oyster sauce  with fresh tomatoes with green pepper in black bean sauce","image":"beef-dish.jpg","imageAlt":"Beef Dish","category":"appetizer","quantity":5},{"id":"m40","name":"Breakfast Appetizer","price":50,"description":"lorem ipsumhhf jhkrifr aspertjd mongodnr fffh urrr gkrbrefk","image":"appetizer.jpg","imageAlt":"Breakfast Appetizer","category":"appetizer","quantity":1},{"id":"m41","name":"Breakfast light Appetizer","price":20,"description":"lorem ipsumhhf jhkrifr aspertjd mongodnr fffh urrr gkrbrefk ","image":"breakfast.jpeg","imageAlt":"Breakfast light Appetizer","category":"appetizer","quantity":1}],"customer":{"fullName":"Jaji Moshood","phone":"08090686548","email":"Jaji.moshood1297@gmail.com","address":"Lagos","direction":"j","payMethod":"payOnDelivery","amount":583.32}},{"id":"842.7796587750973","items":[],"customer":{"fullName":"Jaji Moshood","phone":"08090686548","email":"Jaji.moshood1297@gmail.com","address":"Lagos","direction":"a","payMethod":"payOnDelivery","amount":13.32}},{"id":"246.12415868918447","items":[{"id":"m39","name":"Beef Dish","price":100,"description":"Stir fried shredded beef with oyster sauce  with fresh tomatoes with green pepper in black bean sauce","image":"beef-dish.jpg","imageAlt":"Beef Dish","category":"appetizer","quantity":7}],"customer":{"fullName":"Jaji Moshood","phone":"08090686548","email":"Jaji.moshood1297@gmail.com","address":"Lagos","direction":"a","payMethod":"payOnDelivery","amount":713.32}},{"id":"870.2675344330706","items":[{"id":"m39","name":"Beef Dish","price":100,"description":"Stir fried shredded beef with oyster sauce  with fresh tomatoes with green pepper in black bean sauce","image":"beef-dish.jpg","imageAlt":"Beef Dish","category":"appetizer","quantity":7}],"customer":{"fullName":"Jaji Moshood","phone":"08090686548","email":"Jaji.moshood1297@gmail.com","address":"Lagos","direction":"j","payMethod":"payOnDelivery","amount":713.32}},{"id":"310.316768102241","items":[{"id":"m23","name":"Cat fish pepper soup","price":0,"description":"lorem ipsumhhf jhkrifr aspertjd mongodnr fffh urrr gkrbrefk ","image":"catPsoup.jpeg","imageAlt":"Cat fish pepper soup","category":"local","quantity":2},{"id":"m24","name":"Goat meat pepper soup","price":0,"description":"lorem ipsumhhf jhkrifr aspertjd mongodnr fffh urrr gkrbrefk ","image":"meatPsoup.jpeg","imageAlt":"Goat meat pepper soup","category":"local","quantity":1},{"id":"m39","name":"Beef Dish","price":100,"description":"Stir fried shredded beef with oyster sauce  with fresh tomatoes with green pepper in black bean sauce","image":"beef-dish.jpg","imageAlt":"Beef Dish","category":"appetizer","quantity":1},{"id":"m40","name":"Breakfast Appetizer","price":50,"description":"lorem ipsumhhf jhkrifr aspertjd mongodnr fffh urrr gkrbrefk","image":"appetizer.jpg","imageAlt":"Breakfast Appetizer","category":"appetizer","quantity":1}],"customer":{"fullName":"Jaji Moshood","phone":"08090686548","email":"Jaji.moshood1297@gmail.com","address":"Lagos","direction":"j","payMethod":"payOnDelivery","amount":163.32}},{"id":"403.68374963578304","items":[{"id":"m23","name":"Cat fish pepper soup","price":0,"description":"lorem ipsumhhf jhkrifr aspertjd mongodnr fffh urrr gkrbrefk ","image":"catPsoup.jpeg","imageAlt":"Cat fish pepper soup","category":"local","quantity":2},{"id":"m24","name":"Goat meat pepper soup","price":0,"description":"lorem ipsumhhf jhkrifr aspertjd mongodnr fffh urrr gkrbrefk ","image":"meatPsoup.jpeg","imageAlt":"Goat meat pepper soup","category":"local","quantity":1},{"id":"m39","name":"Beef Dish","price":100,"description":"Stir fried shredded beef with oyster sauce  with fresh tomatoes with green pepper in black bean sauce","image":"beef-dish.jpg","imageAlt":"Beef Dish","category":"appetizer","quantity":1},{"id":"m40","name":"Breakfast Appetizer","price":50,"description":"lorem ipsumhhf jhkrifr aspertjd mongodnr fffh urrr gkrbrefk","image":"appetizer.jpg","imageAlt":"Breakfast Appetizer","category":"appetizer","quantity":1}],"customer":{"fullName":"Jaji Moshood","phone":"08090686548","email":"Jaji.moshood1297@gmail.com","address":"Lagos","direction":"hi","payMethod":"payOnDelivery","amount":163.32}},{"id":"653.1917332018664","items":[{"id":"m23","name":"Cat fish pepper soup","price":0,"description":"lorem ipsumhhf jhkrifr aspertjd mongodnr fffh urrr gkrbrefk ","image":"catPsoup.jpeg","imageAlt":"Cat fish pepper soup","category":"local","quantity":2},{"id":"m24","name":"Goat meat pepper soup","price":0,"description":"lorem ipsumhhf jhkrifr aspertjd mongodnr fffh urrr gkrbrefk ","image":"meatPsoup.jpeg","imageAlt":"Goat meat pepper soup","category":"local","quantity":1},{"id":"m39","name":"Beef Dish","price":100,"description":"Stir fried shredded beef with oyster sauce  with fresh tomatoes with green pepper in black bean sauce","image":"beef-dish.jpg","imageAlt":"Beef Dish","category":"appetizer","quantity":1},{"id":"m40","name":"Breakfast Appetizer","price":50,"description":"lorem ipsumhhf jhkrifr aspertjd mongodnr fffh urrr gkrbrefk","image":"appetizer.jpg","imageAlt":"Breakfast Appetizer","category":"appetizer","quantity":1}],"customer":{"fullName":"Jaji Moshood","phone":"08090686548","email":"Jaji.moshood1297@gmail.com","address":"Lagos","direction":"k","payMethod":"payOnDelivery","amount":163.32}},{"id":"311.71954255545864","items":[{"id":"m39","name":"Beef Dish","price":100,"description":"Stir fried shredded beef with oyster sauce  with fresh tomatoes with green pepper in black bean sauce","image":"beef-dish.jpg","imageAlt":"Beef Dish","category":"appetizer","quantity":11},{"id":"m40","name":"Breakfast Appetizer","price":50,"description":"lorem ipsumhhf jhkrifr aspertjd mongodnr fffh urrr gkrbrefk","image":"appetizer.jpg","imageAlt":"Breakfast Appetizer","category":"appetizer","quantity":1},{"id":"m41","name":"Breakfast light Appetizer","price":20,"description":"lorem ipsumhhf jhkrifr aspertjd mongodnr fffh urrr gkrbrefk ","image":"breakfast.jpeg","imageAlt":"Breakfast light Appetizer","category":"appetizer","quantity":1}],"customer":{"fullName":"Jaji Moshood","phone":"08090686548","email":"Jaji.moshood1297@gmail.com","address":"Lagos","direction":"a","payMethod":"payOnDelivery","amount":1183.32}},{"id":"909.7041774928912","items":[{"id":"m39","name":"Beef Dish","price":100,"description":"Stir fried shredded beef with oyster sauce  with fresh tomatoes with green pepper in black bean sauce","image":"beef-dish.jpg","imageAlt":"Beef Dish","category":"appetizer","quantity":18},{"id":"m40","name":"Breakfast Appetizer","price":50,"description":"lorem ipsumhhf jhkrifr aspertjd mongodnr fffh urrr gkrbrefk","image":"appetizer.jpg","imageAlt":"Breakfast Appetizer","category":"appetizer","quantity":1},{"id":"m41","name":"Breakfast light Appetizer","price":20,"description":"lorem ipsumhhf jhkrifr aspertjd mongodnr fffh urrr gkrbrefk ","image":"breakfast.jpeg","imageAlt":"Breakfast light Appetizer","category":"appetizer","quantity":1}],"customer":{"fullName":"Jaji Moshood","phone":"08090686548","email":"Jaji.moshood1297@gmail.com","address":"Lagos","direction":"j","payMethod":"payOnDelivery","amount":1883.32}},{"id":"188.0103257857595","items":[{"id":"m39","name":"Beef Dish","price":100,"description":"Stir fried shredded beef with oyster sauce  with fresh tomatoes with green pepper in black bean sauce","image":"beef-dish.jpg","imageAlt":"Beef Dish","category":"appetizer","quantity":8}],"customer":{"fullName":"Jaji Moshood","phone":"08090686548","email":"Jaji.moshood1297@gmail.com","address":"Lagos","direction":"a","payMethod":"payOnDelivery","amount":813.32}},{"id":"950.5841944262983","items":[{"id":"m39","name":"Beef Dish","price":100,"description":"Stir fried shredded beef with oyster sauce  with fresh tomatoes with green pepper in black bean sauce","image":"beef-dish.jpg","imageAlt":"Beef Dish","category":"appetizer","quantity":9}],"customer":{"fullName":"Jaji Moshood","phone":"08090686548","email":"Jaji.moshood1297@gmail.com","address":"Lagos","direction":"a","payMethod":"payOnDelivery","amount":913.32}},{"id":"526.9375706207575","items":[{"id":"m39","name":"Beef Dish","price":100,"description":"Stir fried shredded beef with oyster sauce  with fresh tomatoes with green pepper in black bean sauce","image":"beef-dish.jpg","imageAlt":"Beef Dish","category":"appetizer","quantity":10}],"customer":{"fullName":"Jaji Moshood","phone":"08090686548","email":"Jaji.moshood1297@gmail.com","address":"Lagos","direction":"j","payMethod":"payOnDelivery","amount":1013.32}},{"id":"892.6092033729378","items":[{"id":"m39","name":"Beef Dish","price":100,"description":"Stir fried shredded beef with oyster sauce  with fresh tomatoes with green pepper in black bean sauce","image":"beef-dish.jpg","imageAlt":"Beef Dish","category":"appetizer","quantity":11}],"customer":{"fullName":"Jaji Moshood","phone":"08090686548","email":"Jaji.moshood1297@gmail.com","address":"Lagos","direction":"ola","payMethod":"payOnDelivery","amount":1113.32}},{"id":"961.8653485908524","items":[{"id":"m39","name":"Beef Dish","price":100,"description":"Stir fried shredded beef with oyster sauce  with fresh tomatoes with green pepper in black bean sauce","image":"beef-dish.jpg","imageAlt":"Beef Dish","category":"appetizer","quantity":7}],"customer":{"fullName":"Jaji Moshood","phone":"08090686548","email":"Jaji.moshood1297@gmail.com","address":"Lagos","direction":"k","payMethod":"payOnDelivery","amount":713.32}},{"id":"919.055606036246","items":[{"id":"m39","name":"Beef Dish","price":100,"description":"Stir fried shredded beef with oyster sauce  with fresh tomatoes with green pepper in black bean sauce","image":"beef-dish.jpg","imageAlt":"Beef Dish","category":"appetizer","quantity":7}],"customer":{"fullName":"Jaji Moshood","phone":"08090686548","email":"Jaji.moshood1297@gmail.com","address":"Lagos","direction":"k","payMethod":"payOnDelivery","amount":713.32}},{"id":"560.0432279445932","items":[{"id":"m39","name":"Beef Dish","price":100,"description":"Stir fried shredded beef with oyster sauce  with fresh tomatoes with green pepper in black bean sauce","image":"beef-dish.jpg","imageAlt":"Beef Dish","category":"appetizer","quantity":7}],"customer":{"fullName":"Jaji Moshood","phone":"08090686548","email":"Jaji.moshood1297@gmail.com","address":"Lagos","direction":"uiii","payMethod":"payOnDelivery","amount":713.32}},{"id":"619.2608290717781","items":[],"customer":{"fullName":"Jaji Moshood","phone":"08090686548","email":"Jaji.moshood1297@gmail.com","address":"Lagos","direction":"ola","payMethod":"payOnDelivery","amount":713.32}},{"id":"124.00572225329176","items":[{"id":"m39","name":"Beef Dish","price":100,"description":"Stir fried shredded beef with oyster sauce  with fresh tomatoes with green pepper in black bean sauce","image":"beef-dish.jpg","imageAlt":"Beef Dish","category":"appetizer","quantity":7},{"id":"m41","name":"Breakfast light Appetizer","price":20,"description":"lorem ipsumhhf jhkrifr aspertjd mongodnr fffh urrr gkrbrefk ","image":"breakfast.jpeg","imageAlt":"Breakfast light Appetizer","category":"appetizer","quantity":1}],"customer":{"fullName":"Jaji Moshood","phone":"08090686548","email":"Jaji.moshood1297@gmail.com","address":"Lagos","direction":"l","payMethod":"payOnDelivery","amount":733.32}},{"id":"242.83655323015617","items":[{"id":"m39","name":"Beef Dish","price":100,"description":"Stir fried shredded beef with oyster sauce  with fresh tomatoes with green pepper in black bean sauce","image":"beef-dish.jpg","imageAlt":"Beef Dish","category":"appetizer","quantity":10}],"customer":{"fullName":"Jaji Moshood","phone":"08090686548","email":"Jaji.moshood1297@gmail.com","address":"Lagos","direction":"s","payMethod":"payOnDelivery","amount":1013.32}},{"id":"244.975521172222","items":[{"id":"m39","name":"Beef Dish","price":100,"description":"Stir fried shredded beef with oyster sauce  with fresh tomatoes with green pepper in black bean sauce","image":"beef-dish.jpg","imageAlt":"Beef Dish","category":"appetizer","quantity":10}],"customer":{"fullName":"Jaji Moshood","phone":"08090686548","email":"Jaji.moshood1297@gmail.com","address":"Lagos","direction":"j","payMethod":"payOnDelivery","amount":1013.32}},{"id":"491.45360498919246","items":[{"id":"m39","name":"Beef Dish","price":100,"description":"Stir fried shredded beef with oyster sauce  with fresh tomatoes with green pepper in black bean sauce","image":"beef-dish.jpg","imageAlt":"Beef Dish","category":"appetizer","quantity":10}],"customer":{"fullName":"Jaji Moshood","phone":"08090686548","email":"Jaji.moshood1297@gmail.com","address":"Lagos","direction":"j","payMethod":"payOnDelivery","amount":1013.32}},{"id":"871.7217813609244","items":[{"id":"m39","name":"Beef Dish","price":100,"description":"Stir fried shredded beef with oyster sauce  with fresh tomatoes with green pepper in black bean sauce","image":"beef-dish.jpg","imageAlt":"Beef Dish","category":"appetizer","quantity":10}],"customer":{"fullName":"Jaji Moshood","phone":"08090686548","email":"Jaji.moshood1297@gmail.com","address":"Lagos","direction":"j","payMethod":"payOnDelivery","amount":1013.32}},{"id":"747.8778659070755","items":[{"id":"m39","name":"Beef Dish","price":100,"description":"Stir fried shredded beef with oyster sauce  with fresh tomatoes with green pepper in black bean sauce","image":"beef-dish.jpg","imageAlt":"Beef Dish","category":"appetizer","quantity":5}],"customer":{"fullName":"Jaji Moshood","phone":"08090686548","email":"Jaji.moshood1297@gmail.com","address":"Lagos","direction":"e","payMethod":"payOnDelivery","amount":513.32}},{"id":"8.591768712994607","items":[{"id":"m39","name":"Beef Dish","price":100,"description":"Stir fried shredded beef with oyster sauce  with fresh tomatoes with green pepper in black bean sauce","image":"beef-dish.jpg","imageAlt":"Beef Dish","category":"appetizer","quantity":7}],"customer":{"fullName":"Jaji Moshood","phone":"08090686548","email":"Jaji.moshood1297@gmail.com","address":"Lagos","direction":"f","payMethod":"payOnDelivery","amount":713.32}},{"id":"369.1907459846475","items":[{"id":"m39","name":"Beef Dish","price":100,"description":"Stir fried shredded beef with oyster sauce  with fresh tomatoes with green pepper in black bean sauce","image":"beef-dish.jpg","imageAlt":"Beef Dish","category":"appetizer","quantity":5}],"customer":{"fullName":"Jaji Moshood","phone":"08090686548","email":"Jaji.moshood1297@gmail.com","address":"Lagos","direction":"d","payMethod":"payOnDelivery","amount":513.32}},{"id":"320.72733398107124","items":[{"id":"m39","name":"Beef Dish","price":100,"description":"Stir fried shredded beef with oyster sauce  with fresh tomatoes with green pepper in black bean sauce","image":"beef-dish.jpg","imageAlt":"Beef Dish","category":"appetizer","quantity":4}],"customer":{"fullName":"Jaji Moshood","phone":"08090686548","email":"Jaji.moshood1297@gmail.com","address":"Lagos","direction":"a","payMethod":"payOnDelivery","amount":413.32}},{"id":"271.75312890790315","items":[{"id":"m39","name":"Beef Dish","price":100,"description":"Stir fried shredded beef with oyster sauce  with fresh tomatoes with green pepper in black bean sauce","image":"beef-dish.jpg","imageAlt":"Beef Dish","category":"appetizer","quantity":5}],"customer":{"fullName":"Jaji Moshood","phone":"08090686548","email":"Jaji.moshood1297@gmail.com","address":"Lagos","direction":"s","payMethod":"payOnDelivery","amount":513.32}},{"id":"397.2359461407413","items":[{"id":"m39","name":"Beef Dish","price":100,"description":"Stir fried shredded beef with oyster sauce  with fresh tomatoes with green pepper in black bean sauce","image":"beef-dish.jpg","imageAlt":"Beef Dish","category":"appetizer","quantity":4},{"id":"m7","name":"Wraped Chicken Shawarma","price":0,"description":"Tender, juicy, and perfectly spiced grilled chicken wrapped in pita bread or tortilla with delicious homemade yogurt-garlic sauce. Try this quick and easy grilled Chicken Shawarma and enjoy the explosion of Middle Eastern flavors with every bite!","image":"shawarma.jpeg","imageAlt":"Wraped Chicken Shawarma","category":"sandwich&wraps","quantity":1}],"customer":{"fullName":"Jaji Moshood","phone":"08090686548","email":"Jaji.moshood1297@gmail.com","address":"Lagos","direction":"a","payMethod":"payOnDelivery","amount":413.32}}]